COPYING
MANIFEST.in
README.md
requirements.txt
setup.cfg
setup.py
s3url/__init__.py
s3url/s3.py
s3url/time.py
s3url/version.py
s3url.egg-info/PKG-INFO
s3url.egg-info/SOURCES.txt
s3url.egg-info/dependency_links.txt
s3url.egg-info/requires.txt
s3url.egg-info/top_level.txt
scripts/s3url