Metadata-Version: 1.1
Name: s3url
Version: 0.1.6
Summary: A simple command line utility for generating time-sensitive, sharable urls for private s3 files
Home-page: https://github.com/fordhurley/s3url
Author: Ford Hurley
Author-email: ford.hurley@gmail.com
License: WTFPL v2
Platform: UNKNOWN
Classifier: Programming Language :: Python
Classifier: Programming Language :: Python :: 2
Classifier: Environment :: Console
